agentos/__init__.py
agentos/agent_run.py
agentos/cli.py
agentos/core.py
pcs/__init__.py
pcs/argument_set.py
pcs/component.py
pcs/component_run.py
pcs/exceptions.py
pcs/identifiers.py
pcs/registry.py
pcs/repo.py
pcs/run.py
pcs/run_command.py
pcs/specs.py
pcs/utils.py
pcs/version.py
pcs/virtual_env.py
agentos-0.2.0.dist-info/LICENSE
agentos-0.2.0.dist-info/METADATA
agentos-0.2.0.dist-info/WHEEL
agentos-0.2.0.dist-info/entry_points.txt
agentos-0.2.0.dist-info/top_level.txt
agentos-0.2.0.dist-info/RECORD
