Metadata-Version: 2.1
Name: agentos
Version: 0.2.0
Summary: AgentOS is a command line interface and python developer API for building, running, and sharing flexible learning agents.
Home-page: https://agentos.org
Author: Andy Konwinski
License: Apache License 2.0
Project-URL: Source Code, https://github.com/agentos-project/agentos
Keywords: reinforcement learning ai agent
Platform: UNKNOWN
Requires-Python: >=3.5
License-File: LICENSE
Requires-Dist: click (>=7.0)
Requires-Dist: pyyaml (>=5.4.1)
Requires-Dist: mlflow (>=1.20.2)
Requires-Dist: dulwich (==0.20.28)
Requires-Dist: requests (>=2.21.0)
Requires-Dist: python-dotenv (>=0.19.1)
Requires-Dist: rich (>=10.15.2)
Requires-Dist: dill (>=0.3.4)
